visionts/__init__.py
visionts/model.py
visionts/models_mae.py
visionts/pos_embed.py
visionts/util.py
visionts-1.0.1.dist-info/LICENSE
visionts-1.0.1.dist-info/METADATA
visionts-1.0.1.dist-info/WHEEL
visionts-1.0.1.dist-info/top_level.txt
visionts-1.0.1.dist-info/RECORD
