Metadata-Version: 2.1
Name: visionts
Version: 1.0.1
Summary: Using a visual MAE for time series forecasting.
Home-page: https://github.com/Keytoyze/VisionTS
Author: Mouxiang Chen, Lefei Shen
Author-email: chenmx@zju.edu.cn
Requires-Python: >=3.6
License-File: LICENSE
Requires-Dist: torch
Requires-Dist: torchvision
Requires-Dist: einops
Requires-Dist: numpy
Requires-Dist: timm
Requires-Dist: pandas
Requires-Dist: huggingface-hub
